[
    {
        "name": "Battle for Zendikar",
        "code": "BFZ",
        "releaseDate": "2015-10-02",
        "type": "expansion",
        "block": "Battle for Zendikar",
        "onlineOnly": false
    },
    {
        "name": "Commander 2015",
        "code": "C15",
        "releaseDate": "2015-11-13",
        "type": "commander",
        "block": "Commander",
        "onlineOnly": false
    },
    {
        "name": "Fate Reforged Clash Pack",
        "code": "CP2",
        "releaseDate": "2015-01-23",
        "type": "starter",
        "block": "Khans of Tarkir",
        "onlineOnly": false
    },
    {
        "name": "Magic Origins Clash Pack",
        "code": "CP3",
        "releaseDate": "2015-07-17",
        "type": "starter",
        "block": null,
        "onlineOnly": false
    },
    {
        "name": "Duel Decks: Elspeth vs. Kiora",
        "code": "DDO",
        "releaseDate": "2015-02-27",
        "type": "duel_deck",
        "block": null,
        "onlineOnly": false
    },
    {
        "name": "Duel Decks: Zendikar vs. Eldrazi",
        "code": "DDP",
        "releaseDate": "2015-08-28",
        "type": "duel_deck",
        "block": null,
        "onlineOnly": false
    },
    {
        "name": "Dragons of Tarkir",
        "code": "DTK",
        "releaseDate": "2015-03-27",
        "type": "expansion",
        "block": "Khans of Tarkir",
        "onlineOnly": false
    },
    {
        "name": "Zendikar Expeditions",
        "code": "EXP",
        "releaseDate": "2015-10-02",
        "type": "masterpiece",
        "block": "Battle for Zendikar",
        "onlineOnly": false
    },
    {
        "name": "Friday Night Magic 2015",
        "code": "F15",
        "releaseDate": "2015-01-01",
        "type": "promo",
        "block": "Friday Night Magic",
        "onlineOnly": false
    },
    {
        "name": "Fate Reforged",
        "code": "FRF",
        "releaseDate": "2015-01-23",
        "type": "expansion",
        "block": "Khans of Tarkir",
        "onlineOnly": false
    },
    {
        "name": "Judge Gift Cards 2015",
        "code": "J15",
        "releaseDate": "2015-01-01",
        "type": "promo",
        "block": "Judge Gift Cards",
        "onlineOnly": false
    },
    {
        "name": "League Tokens 2015",
        "code": "L15",
        "releaseDate": "2015-01-01",
        "type": "token",
        "block": null,
        "onlineOnly": false
    },
    {
        "name": "Modern Masters 2015",
        "code": "MM2",
        "releaseDate": "2015-05-22",
        "type": "masters",
        "block": null,
        "onlineOnly": false
    },
    {
        "name": "Commander 2015 Oversized",
        "code": "OC15",
        "releaseDate": "2015-11-13",
        "type": "memorabilia",
        "block": "Commander",
        "onlineOnly": false
    },
    {
        "name": "Magic Origins",
        "code": "ORI",
        "releaseDate": "2015-07-17",
        "type": "core",
        "block": "Core Set",
        "onlineOnly": false
    },
    {
        "name": "Battle for Zendikar Promos",
        "code": "PBFZ",
        "releaseDate": "2015-10-02",
        "type": "promo",
        "block": "Battle for Zendikar",
        "onlineOnly": false
    },
    {
        "name": "Dragons of Tarkir Promos",
        "code": "PDTK",
        "releaseDate": "2015-03-27",
        "type": "promo",
        "block": "Khans of Tarkir",
        "onlineOnly": false
    },
    {
        "name": "Fate Reforged Promos",
        "code": "PFRF",
        "releaseDate": "2015-01-23",
        "type": "promo",
        "block": "Khans of Tarkir",
        "onlineOnly": false
    },
    {
        "name": "Magic Origins Promos",
        "code": "PORI",
        "releaseDate": "2015-07-17",
        "type": "promo",
        "block": null,
        "onlineOnly": false
    },
    {
        "name": "San Diego Comic-Con 2015",
        "code": "PS15",
        "releaseDate": "2015-07-09",
        "type": "promo",
        "block": null,
        "onlineOnly": false
    },
    {
        "name": "BFZ Standard Series",
        "code": "PSS1",
        "releaseDate": "2015-10-02",
        "type": "promo",
        "block": "Battle for Zendikar",
        "onlineOnly": false
    },
    {
        "name": "Tarkir Dragonfury",
        "code": "PTKDF",
        "releaseDate": "2015-04-03",
        "type": "promo",
        "block": "Khans of Tarkir",
        "onlineOnly": false
    },
    {
        "name": "Legendary Cube Prize Pack",
        "code": "PZ1",
        "releaseDate": "2015-11-18",
        "type": "treasure_chest",
        "block": null,
        "onlineOnly": true
    },
    {
        "name": "Tempest Remastered",
        "code": "TPR",
        "releaseDate": "2015-05-06",
        "type": "masters",
        "block": null,
        "onlineOnly": true
    },
    {
        "name": "Ugin's Fate",
        "code": "UGIN",
        "releaseDate": "2015-01-17",
        "type": "promo",
        "block": "Khans of Tarkir",
        "onlineOnly": false
    },
    {
        "name": "From the Vault: Angels",
        "code": "V15",
        "releaseDate": "2015-08-21",
        "type": "from_the_vault",
        "block": null,
        "onlineOnly": false
    }
]